ca_certificates/__init__.py
tosa_serialization_lib-0.0.0.dist-info/METADATA
tosa_serialization_lib-0.0.0.dist-info/WHEEL
tosa_serialization_lib-0.0.0.dist-info/top_level.txt
tosa_serialization_lib-0.0.0.dist-info/RECORD
