Metadata-Version: 2.4
Name: tosa_serialization_lib
Version: 0.0.0
Summary: Dummy tosa_serialization_lib package for PyPI
Author-email: Your Name <you@example.com>
Requires-Python: >=3.7
